d_flipflop.v
module d_flipflop (
    output reg Q,
    input wire D,Clk,Rst
);
always @(posedge Clk) begin
    if (!Rst) begin
        Q=1'b0;
    end
    else
    begin
        Q=D;
    end
end
endmodule

d_flipflop_tb.v
`include "d_flipflop.v"
module d_flipflop_tb (
);
    reg D,Clk,Rst;
    wire Q;
    d_flipflop Dff(.D(D),.Clk(Clk),.Rst(Rst),.Q(Q));
    always @(Clk) begin
        #15 Clk=!Clk;
    end
    initial begin
        $dumpfile("d_flipflop_tb.vcd");
        $dumpvars(0,d_flipflop_tb);
        $monitor("Time=%t\tD=%b\tClk=%b\tRst=%b\tQ=%b\n",$time,D,Clk,Rst,Q);
        Rst=1'b1;
        D=1'b1;
        #5
        Clk=1'b1;
        #10
        Clk=1'b0;
        D=1'b0;
        #5
        Clk=1'b1;
        #10
        Clk=1'b0;
        D=1'b1;
        #5
        Clk=1'b1;
        #10
        Clk=1'b0;
        Rst=1'b0;
        #5
        Clk=1'b1;
        #10
        Clk=1'b0;

    end
endmodule

d_flipflop_tb.vcd
$date
	Thu Nov 02 19:01:35 2023
$end
$version
	Icarus Verilog
$end
$timescale
	1s
$end
$scope module d_flipflop_tb $end
$var wire 1 ! Q $end
$var reg 1 " Clk $end
$var reg 1 # D $end
$var reg 1 $ Rst $end
$scope module Dff $end
$var wire 1 " Clk $end
$var wire 1 # D $end
$var wire 1 $ Rst $end
$var reg 1 ! Q $end
$upscope $end
$upscope $end
$enddefinitions $end
$comment Show the parameter values. $end
$dumpall
$end
#0
$dumpvars
1$
1#
x"
x!
$end
#5
1!
1"
#15
0#
0"
#20
0!
1"
#30
1#
0"
#35
1!
1"
#45
0$
0"
#50
0!
1"
