full_adder.v
module full_adder (
    input wire  A,B,Cin,
    output wire Sum,Cout
);
    assign Sum=A^B^Cin;
    assign Cout=(A&Cin)|(B&Cin)|(A&B);
endmodule

full_adder_tb.v
`include "full_adder.v"
module full_adder_tb (
);
    reg A,B,Cin;
    wire Sum,Cout;
    full_adder FA1(.A(A),.B(B),.Cin(Cin),.Sum(Sum),.Cout(Cout));
    initial begin
        $dumpfile("full_adder_tb.vcd");
        $dumpvars(0,full_adder_tb);
        $monitor("Time=%t\tA=%b\tB=%b\tCin=%b\tSum=%b\tCout=%b\n",$time,A,B,Cin,Sum,Cout);
        A=1'b0;B=1'b0;Cin=1'b0;
        #15
        A=1'b0;B=1'b0;Cin=1'b1;
        #15
        A=1'b0;B=1'b1;Cin=1'b0;
        #15
        A=1'b0;B=1'b1;Cin=1'b1;
        #15
        A=1'b1;B=1'b0;Cin=1'b0;
        #15
        A=1'b1;B=1'b0;Cin=1'b1;
        #15
        A=1'b1;B=1'b1;Cin=1'b0;
        #15
        A=1'b1;B=1'b1;Cin=1'b1;
    end
endmodule

full_adder_tb.vcd
$date
	Thu Nov 02 18:27:50 2023
$end
$version
	Icarus Verilog
$end
$timescale
	1s
$end
$scope module full_adder_tb $end
$var wire 1 ! Sum $end
$var wire 1 " Cout $end
$var reg 1 # A $end
$var reg 1 $ B $end
$var reg 1 % Cin $end
$scope module FA1 $end
$var wire 1 # A $end
$var wire 1 $ B $end
$var wire 1 % Cin $end
$var wire 1 " Cout $end
$var wire 1 ! Sum $end
$upscope $end
$upscope $end
$enddefinitions $end
$comment Show the parameter values. $end
$dumpall
$end
#0
$dumpvars
0%
0$
0#
0"
0!
$end
#15
1!
1%
#30
0%
1$
#45
1"
0!
1%
#60
0"
1!
0%
0$
1#
#75
1"
0!
1%
#90
0%
1$
#105
1!
1%
