memory.v
module memory #(
    parameter BIT_DEPTH=8,
    parameter ADDRESS_LINES=7
) (
    output reg [BIT_DEPTH-1:0] Dout,
    input wire [BIT_DEPTH-1:0] Din,
    input wire Clk,RD,WR,CS,
    input wire [ADDRESS_LINES-1:0] Add
);
parameter LENGTH= 2**ADDRESS_LINES;
    reg [BIT_DEPTH-1:0] mem[LENGTH-1:0];
always @(negedge Clk ) begin
    if(CS) begin
        Dout='hzz;
    end
    else begin
        if(!WR) begin
            mem[Add]=Din;
        end
        if(!RD) begin
            Dout=mem[Add];
        end
        else begin
            Dout='hzz;
        end
    end
    
end
    
endmodule

memory_tb.v
`include "memory.v"

module memory_tb ();
    wire [7:0] Dout;
    reg [7:0] Din;
    reg Clk,RD,WR,CS;
    reg [6:0] Add;

    memory #(.BIT_DEPTH(8),.ADDRESS_LINES(7)) mem(.Dout(Dout),.Din(Din),.Clk(Clk),.RD(RD),.WR(WR),.CS(CS),.Add(Add));

    initial begin
        $dumpfile("memory_tb.vcd");
        $dumpvars(0,memory_tb);
        $monitor("Time=%t\tDout=%h\tDin=%h\tClk=%b\tRD=%b\tWR=%b\tCS=%b\tAdd=%b\n",$time,Dout,Din,Clk,RD,WR,CS,Add);
        Din=8'h00;
        RD=1'b1;
        WR=1'b1;
        CS=1'b1;
        Add=7'd0;
        Clk=1'b1;
        #10
        Clk=1'b0;
        #10
        Din=8'h35;
        RD=1'b1;
        WR=1'b0;
        CS=1'b0;
        Add=7'd0;
        Clk=1'b1;
        #10
        Clk=1'b0;
        #10
        Din=8'h53;
        RD=1'b1;
        WR=1'b0;
        CS=1'b0;
        Add=7'd1;
        Clk=1'b1;
        #10
        Clk=1'b0;
        #10
        Din=8'h35;
        RD=1'b0;
        WR=1'b1;
        CS=1'b0;
        Add=7'd0;
        Clk=1'b1;
        #10
        Clk=1'b0;
        #10
        Din=8'h53;
        RD=1'b0;
        WR=1'b0;
        CS=1'b0;
        Add=7'd1;
        Clk=1'b1;
        #10
        Clk=1'b0;
        #10
        Din=8'h53;
        RD=1'b0;
        WR=1'b0;
        CS=1'b1;
        Add=7'd1;
        Clk=1'b1;
        #10
        Clk=1'b0;

    end
endmodule

memory_tb.vcd
$date
	Fri Nov 03 01:38:47 2023
$end
$version
	Icarus Verilog
$end
$timescale
	1s
$end
$scope module memory_tb $end
$var wire 8 ! Dout [7:0] $end
$var reg 7 " Add [6:0] $end
$var reg 1 # CS $end
$var reg 1 $ Clk $end
$var reg 8 % Din [7:0] $end
$var reg 1 & RD $end
$var reg 1 ' WR $end
$scope module mem $end
$var wire 7 ( Add [6:0] $end
$var wire 1 # CS $end
$var wire 1 $ Clk $end
$var wire 8 ) Din [7:0] $end
$var wire 1 & RD $end
$var wire 1 ' WR $end
$var parameter 32 * ADDRESS_LINES $end
$var parameter 32 + BIT_DEPTH $end
$var parameter 32 , LENGTH $end
$var reg 8 - Dout [7:0] $end
$upscope $end
$upscope $end
$enddefinitions $end
$comment Show the parameter values. $end
$dumpall
b10000000 ,
b1000 +
b111 *
$end
#0
$dumpvars
bx -
b0 )
b0 (
1'
1&
b0 %
1$
1#
b0 "
bx !
$end
#10
bz !
bz -
0$
#20
1$
0#
0'
b110101 %
b110101 )
#30
0$
#40
1$
b1 "
b1 (
b1010011 %
b1010011 )
#50
0$
#60
1$
b0 "
b0 (
1'
0&
b110101 %
b110101 )
#70
b110101 !
b110101 -
0$
#80
1$
b1 "
b1 (
0'
b1010011 %
b1010011 )
#90
b1010011 !
b1010011 -
0$
#100
1$
1#
#110
bz !
bz -
0$
