register.v
module register #(//A gated register with tristate buffer at output and input
    parameter n =8 
) (
    output reg[n-1:0] Q,
    input wire[n-1:0] D,
    input wire Clk,RD,WR,Rst
);
    reg [n-1:0] Data;
    always @(negedge Clk) begin
        if (!RD) begin
            Q=Data;
        end
        else begin
            Q='hz;
        end
        if (!WR) begin
            Data=D;
        end
        if (!Rst) begin
            Data='d0;
        end
    end
endmodule

register_tb.v
`include "register.v"

module register_tb ();
    wire[7:0] Q;
    reg[7:0] D;
    reg Clk,RD,WR,Rst;

    register #(.n(8)) rg (.Q(Q),.D(D),.Clk(Clk),.RD(RD),.WR(WR),.Rst(Rst));

    initial begin
        $dumpfile("$register_tb.vcd");
        $dumpvars(0,register_tb);
        $monitor("Time=%t\tD=%h\tClk=%b\tRD=%b\tWR=%b\tRst=%b\tQ=%h\n",$time,D,Clk,RD,WR,Rst,Q);
        RD=1'b1;
        WR=1'b1;
        Rst=1'b1;
        D=8'h00;
        Clk=1'b1;
        #10;
        Clk=1'b0;
        #10
        RD=1'b1;
        WR=1'b0;
        Rst=1'b1;
        D=8'h35;
        Clk=1'b1;
        #10;
        Clk=1'b0;
        #10
        RD=1'b0;
        WR=1'b1;
        Rst=1'b1;
        D=8'h35;
        Clk=1'b1;
        #10;
        Clk=1'b0;
        #10
        RD=1'b1;
        WR=1'b1;
        Rst=1'b0;
        D=8'h35;
        Clk=1'b1;
        #10;
        Clk=1'b0;
        #10
        RD=1'b0;
        WR=1'b1;
        Rst=1'b1;
        D=8'h35;
        Clk=1'b1;
        #10;
        Clk=1'b0;
    end
endmodule

register_tb.vcd
$date
	Fri Nov 03 02:34:02 2023
$end
$version
	Icarus Verilog
$end
$timescale
	1s
$end
$scope module register_tb $end
$var wire 8 ! Q [7:0] $end
$var reg 1 " Clk $end
$var reg 8 # D [7:0] $end
$var reg 1 $ RD $end
$var reg 1 % Rst $end
$var reg 1 & WR $end
$scope module rg $end
$var wire 1 " Clk $end
$var wire 8 ' D [7:0] $end
$var wire 1 $ RD $end
$var wire 1 % Rst $end
$var wire 1 & WR $end
$var parameter 32 ( n $end
$var reg 8 ) Data [7:0] $end
$var reg 8 * Q [7:0] $end
$upscope $end
$upscope $end
$enddefinitions $end
$comment Show the parameter values. $end
$dumpall
b1000 (
$end
#0
$dumpvars
bx *
bx )
b0 '
1&
1%
1$
b0 #
1"
bx !
$end
#10
bz !
bz *
0"
#20
1"
b110101 #
b110101 '
0&
#30
b110101 )
0"
#40
1"
1&
0$
#50
b110101 !
b110101 *
0"
#60
1"
0%
1$
#70
b0 )
bz !
bz *
0"
#80
1"
1%
0$
#90
b0 !
b0 *
0"
